pynYNAB/Client.py
pynYNAB/ClientFactory.py
pynYNAB/KeyGenerator.py
pynYNAB/ObjClient.py
pynYNAB/__init__.py
pynYNAB/connection.py
pynYNAB/exceptions.py
pynYNAB/utils.py
pynYNAB/schema/Client.py
pynYNAB/schema/Entity.py
pynYNAB/schema/RootEntity.py
pynYNAB/schema/__init__.py
pynYNAB/schema/budget.py
pynYNAB/schema/catalog.py
pynYNAB/schema/roots.py
pynYNAB/schema/types.py
pynYNAB/scripts/__init__.py
pynYNAB/scripts/__main__.py
pynYNAB/scripts/csvimport.py
pynYNAB/scripts/generate_doc.py
pynYNAB/scripts/helpers.py
pynYNAB/scripts/ofximport.py
pynYNAB-0.7.1.dist-info/DESCRIPTION.rst
pynYNAB-0.7.1.dist-info/METADATA
pynYNAB-0.7.1.dist-info/RECORD
pynYNAB-0.7.1.dist-info/WHEEL
pynYNAB-0.7.1.dist-info/entry_points.txt
pynYNAB-0.7.1.dist-info/metadata.json
pynYNAB-0.7.1.dist-info/top_level.txt
test_live/__init__.py
test_live/common.py
test_live/get_webapp_code.py
test_live/test_live.py
tests/__init__.py
tests/changed_entities.py
tests/common_mock.py
tests/date.py
tests/live_test.py
tests/test.py
tests/test_conversion_functions.py
tests/test_csvimport.py
tests/test_merge.py
tests/test_persist.py
tests/test_scripts.py
tests/test_unicode.py
tests/tests_connection.py
tests/tests_new_api.py
tests/tests_operations.py
tests/wrongpush.py
