Metadata-Version: 2.0
Name: pynYNAB
Version: 0.7.1
Summary: Library for working with the nYNAB private APIBudget/Transactions Read/Write/Migration tools
Home-page: https://github.com/rienafairefr/nYNABapi
Author: rienafairefr
Author-email: rienafairefr@gmail.com
License: MIT
Download-URL: https://github.com/rienafairefr/nYNABapi/tarball/master
Keywords: nynab,ynab
Platform: UNKNOWN
Classifier: Development Status :: 3 - Alpha
Classifier: Intended Audience :: Developers
Classifier: Intended Audience :: Financial and Insurance Industry
Classifier: Topic :: Software Development :: Libraries :: Python Modules
Classifier: Topic :: Utilities
Classifier: Topic :: Office/Business
Classifier: Topic :: Office/Business :: Financial
Classifier: License :: OSI Approved :: MIT License
Classifier: Operating System :: OS Independent
Classifier: Natural Language :: English
Classifier: Programming Language :: Python
Classifier: Programming Language :: Python :: 2
Classifier: Programming Language :: Python :: 2.7
Requires-Dist: requests
Requires-Dist: jsontableschema (==0.10.0)
Requires-Dist: unicodecsv
Requires-Dist: six (>=1.5)
Requires-Dist: aenum
Requires-Dist: ofxtools
Requires-Dist: sqlalchemy
Requires-Dist: ynab-api
Requires-Dist: pyYAML
